{
	"info": {
		"_postman_id": "ef84432f-ec76-4b0b-b5be-5e3c76ce1fe0",
		"name": "Dreamteam",
		"schema": "https://schema.getpostman.com/json/collection/v2.1.0/collection.json"
	},
	"item": [
		{
			"name": "User Service",
			"item": [
				{
					"name": "Login",
					"event": [
						{
							"listen": "test",
							"script": {
								"id": "63eae9f7-8135-4f09-8280-728586fbb2e2",
								"exec": [
									"var json = pm.response.json()",
									"tests[\"Response status is 200\"] = responseCode.code === 200",
									"tests[\"Username is 59130500075\"] = pm.expect(json.username).to.eql(\"59130500075\")",
									"tests[\"Firstname is Rattanan\"] = pm.expect(json.firstname).to.eql(\"Rattanan\")",
									"tests[\"Token is defined\"] = json.token !== undefined",
									"tests[\"Response time is accdeptable\"] = responseTime < 3000",
									"pm.globals.set(\"token\", json.token);"
								],
								"type": "text/javascript"
							}
						}
					],
					"request": {
						"method": "POST",
						"header": [
							{
								"key": "Content-Type",
								"name": "Content-Type",
								"value": "application/json",
								"type": "text"
							}
						],
						"body": {
							"mode": "raw",
							"raw": "{\n\t\"username\" : \"59130500075\",\n\t\"password\" : \"57000503195\"\n}"
						},
						"url": {
							"raw": "https://dreamteam-userservice.mybluemix.net/login",
							"protocol": "https",
							"host": [
								"dreamteam-userservice",
								"mybluemix",
								"net"
							],
							"path": [
								"login"
							]
						},
						"description": "Login with username and password"
					},
					"response": [
						{
							"name": "Authentication Login",
							"originalRequest": {
								"method": "POST",
								"header": [
									{
										"key": "Content-Type",
										"name": "Content-Type",
										"value": "application/json",
										"type": "text"
									}
								],
								"body": {
									"mode": "raw",
									"raw": "{\n\t\"username\" : \"59130500128\",\n\t\"password\" : \"82100503195\"\n}"
								},
								"url": {
									"raw": "http://localhost:8080/login",
									"protocol": "http",
									"host": [
										"localhost"
									],
									"port": "8080",
									"path": [
										"login"
									]
								}
							},
							"status": "OK",
							"code": 200,
							"_postman_previewlanguage": "json",
							"header": [
								{
									"key": "Content-Type",
									"value": "application/json;charset=UTF-8"
								},
								{
									"key": "Transfer-Encoding",
									"value": "chunked"
								},
								{
									"key": "Date",
									"value": "Sun, 28 Oct 2018 11:12:48 GMT"
								}
							],
							"cookie": [],
							"body": "{\n    \"studentId\": 59130500128,\n    \"firstname\": \"Tanapat\",\n    \"lastname\": \"Choochot\",\n    \"department\": \"IT\",\n    \"faculty\": \"SIT\",\n    \"studentYear\": 3\n}"
						}
					]
				},
				{
					"name": "Get user with specific studentId",
					"event": [
						{
							"listen": "test",
							"script": {
								"id": "894444a6-bec6-47fd-ad4b-a23fecc9e9d2",
								"exec": [
									"var json = pm.response.json()",
									"tests[\"Response status is 200\"] = responseCode.code === 200",
									"tests[\"Username is 59130500075\"] = pm.expect(json.username).to.eql(\"59130500075\")",
									"tests[\"Firstname is Rattanan\"] = pm.expect(json.firstname).to.eql(\"Rattanan\")",
									"tests[\"Response time is accdeptable\"] = responseTime < 3000"
								],
								"type": "text/javascript"
							}
						}
					],
					"request": {
						"method": "GET",
						"header": [
							{
								"key": "Authorization",
								"value": "{{token}}",
								"type": "text"
							}
						],
						"body": {
							"mode": "raw",
							"raw": ""
						},
						"url": {
							"raw": "https://dreamteam-userservice.mybluemix.net/user/59130500075",
							"protocol": "https",
							"host": [
								"dreamteam-userservice",
								"mybluemix",
								"net"
							],
							"path": [
								"user",
								"59130500075"
							]
						},
						"description": "Get detail of studentId"
					},
					"response": []
				},
				{
					"name": "Get all users in database",
					"event": [
						{
							"listen": "test",
							"script": {
								"id": "875e041c-61b3-4826-8a64-71980c1571ea",
								"exec": [
									"var json = pm.response.json()",
									"tests[\"Response status is 200\"] = responseCode.code === 200",
									"tests[\"Database is not empty\"] = json.length > 0",
									"tests[\"Username is 59130500075\"] = pm.expect(json[0].username).to.eql(\"59130500075\")",
									"tests[\"Firstname is Rattanan\"] = pm.expect(json[0].firstname).to.eql(\"Rattanan\")",
									"tests[\"Response time is accdeptable\"] = responseTime < 3000"
								],
								"type": "text/javascript"
							}
						}
					],
					"request": {
						"method": "GET",
						"header": [
							{
								"key": "Authorization",
								"value": "{{token}}",
								"type": "text"
							}
						],
						"body": {
							"mode": "raw",
							"raw": ""
						},
						"url": {
							"raw": "https://dreamteam-userservice.mybluemix.net/users",
							"protocol": "https",
							"host": [
								"dreamteam-userservice",
								"mybluemix",
								"net"
							],
							"path": [
								"users"
							]
						},
						"description": "List of all user in database"
					},
					"response": []
				},
				{
					"name": "Create user",
					"event": [
						{
							"listen": "test",
							"script": {
								"id": "c51ebde2-1c55-4d74-aef2-8f7ca67c19c9",
								"exec": [
									"var json = pm.response.json()",
									"tests[\"Response status is 201\"] = responseCode.code === 200",
									"tests[\"Username is 59130500089\"] = pm.expect(json.username).to.eql(\"59130500089\")",
									"tests[\"Firstname is Vitsarut\"] = pm.expect(json.firstname).to.eql(\"Vitsarut\")",
									"tests[\"Response time is accdeptable\"] = responseTime < 3000",
									"pm.globals.set(\"userId\", json.id)"
								],
								"type": "text/javascript"
							}
						}
					],
					"request": {
						"method": "POST",
						"header": [
							{
								"key": "Content-Type",
								"name": "Content-Type",
								"value": "application/json",
								"type": "text"
							}
						],
						"body": {
							"mode": "raw",
							"raw": "{\n\t\"username\": \"59130500089\",\n\t\"password\": \"98000503195\",\n\t\"firstname\": \"Vitsarut\",\n\t\"lastname\": \"Udomphol\",\n\t\"department\": \"IT\",\n\t\"faculty\": \"SIT\",\n\t\"year\": \"3\"\n}"
						},
						"url": {
							"raw": "https://dreamteam-userservice.mybluemix.net/user",
							"protocol": "https",
							"host": [
								"dreamteam-userservice",
								"mybluemix",
								"net"
							],
							"path": [
								"user"
							]
						},
						"description": "This request is test to create user with any username, password"
					},
					"response": []
				},
				{
					"name": "Delete user ",
					"event": [
						{
							"listen": "test",
							"script": {
								"id": "7c7e30d9-9ef6-4d46-bb54-04365bc470b2",
								"exec": [
									"var responseUserId = pm.response.json()",
									"var storageUserId = pm.globals.get(\"userId\");",
									"tests[\"Response status is 200\"] = responseCode.code === 200",
									"tests[\"Response is userId = \" + storageUserId] = pm.expect(responseUserId).to.eql(storageUserId)",
									"tests[\"Response time is accdeptable\"] = responseTime < 3000"
								],
								"type": "text/javascript"
							}
						}
					],
					"request": {
						"method": "DELETE",
						"header": [],
						"body": {
							"mode": "raw",
							"raw": ""
						},
						"url": {
							"raw": "https://dreamteam-userservice.mybluemix.net/user/{{userId}}",
							"protocol": "https",
							"host": [
								"dreamteam-userservice",
								"mybluemix",
								"net"
							],
							"path": [
								"user",
								"{{userId}}"
							]
						},
						"description": "This test is use to delete user from database"
					},
					"response": []
				}
			]
		},
		{
			"name": "SubjectList Service",
			"item": [
				{
					"name": "/curriculum",
					"event": [
						{
							"listen": "test",
							"script": {
								"id": "310b0363-fb75-44d1-bd77-e360de3599c9",
								"exec": [
									"pm.test(\"แสดง list ของ curriculum ทั้งหมด\", function(){",
									"    var jsonData = pm.response.json();",
									"    pm.expect(jsonData[0].curriculumId).to.eql(1);",
									"    pm.expect(jsonData[0].curriculumName).to.eql(\"Bachelor of Science Program in Information Technology\");",
									"    pm.expect(jsonData[0].curriculumCode).to.eql(\"B.Sc.IT\");",
									"    pm.expect(jsonData[0].curriculumDescription).to.eql(\"\");",
									"})"
								],
								"type": "text/javascript"
							}
						}
					],
					"request": {
						"method": "GET",
						"header": [],
						"body": {
							"mode": "raw",
							"raw": ""
						},
						"url": {
							"raw": "https://dreamteam-gateway.mybluemix.net/subject-service/curriculums",
							"protocol": "https",
							"host": [
								"dreamteam-gateway",
								"mybluemix",
								"net"
							],
							"path": [
								"subject-service",
								"curriculums"
							]
						}
					},
					"response": []
				},
				{
					"name": "/curriculum/{curriculumId}",
					"event": [
						{
							"listen": "test",
							"script": {
								"id": "09a99723-21a8-4179-8d9f-ad0ea6b713d9",
								"exec": [
									"pm.test(\"แสดง curriculum ที่มี id 1\", function(){",
									"    var jsonData = pm.response.json();",
									"    pm.expect(jsonData.curriculumId).to.eql(1);",
									"    pm.expect(jsonData.curriculumName).to.eql(\"Bachelor of Science Program in Information Technology\");",
									"    pm.expect(jsonData.curriculumCode).to.eql(\"B.Sc.IT\");",
									"    pm.expect(jsonData.curriculumDescription).to.eql(\"\");",
									"})"
								],
								"type": "text/javascript"
							}
						}
					],
					"request": {
						"method": "GET",
						"header": [],
						"body": {
							"mode": "raw",
							"raw": ""
						},
						"url": {
							"raw": "https://dreamteam-gateway.mybluemix.net/subject-service/curriculum/1",
							"protocol": "https",
							"host": [
								"dreamteam-gateway",
								"mybluemix",
								"net"
							],
							"path": [
								"subject-service",
								"curriculum",
								"1"
							]
						}
					},
					"response": []
				},
				{
					"name": "/subjectlist/curriculum/{curriculumId}",
					"event": [
						{
							"listen": "test",
							"script": {
								"id": "05535359-83bc-48a8-a84a-17984145b5a3",
								"exec": [
									"pm.test(\"แสดง subject list ของ curriculumId 1\", function(){",
									"    var jsonData = pm.response.json();",
									"    pm.expect(jsonData[0].subjectId).to.eql(2);",
									"    pm.expect(jsonData[0].subjectName).to.eql(\"IT Fundamental\");",
									"    pm.expect(jsonData[0].subjectDes).to.eql(\"\");",
									"    pm.expect(jsonData[0].isFavorite).to.eql(false);",
									"})"
								],
								"type": "text/javascript"
							}
						}
					],
					"request": {
						"method": "GET",
						"header": [],
						"body": {
							"mode": "raw",
							"raw": ""
						},
						"url": {
							"raw": "https://dreamteam-gateway.mybluemix.net/subject-service/subjectlist/curriculum/1",
							"protocol": "https",
							"host": [
								"dreamteam-gateway",
								"mybluemix",
								"net"
							],
							"path": [
								"subject-service",
								"subjectlist",
								"curriculum",
								"1"
							]
						}
					},
					"response": []
				}
			]
		},
		{
			"name": "Video Service",
			"item": [
				{
					"name": "/videos/{subjectId}",
					"event": [
						{
							"listen": "test",
							"script": {
								"id": "90dc21e4-5fac-41c8-8259-3c13067401ea",
								"exec": [
									"pm.test(\"แสดง list video ของ subjectId 2\", function(){",
									"    var jsonData = pm.response.json();",
									"    pm.expect(jsonData[0].videoId).to.eql(8282);",
									"    pm.expect(jsonData[0].videoName).to.eql(\"INT 101 INFORMATION TECHNOLOGY FUNDAMENTAL G.2\");",
									"    pm.expect(jsonData[0].lecturer).to.eql(\"Siam Yamsaengsung\");",
									"    pm.expect(jsonData[0].videoThumbnail).to.eql(\"https://ngelearning.sit.kmutt.ac.th/api/video_image?id=8282\");",
									"})"
								],
								"type": "text/javascript"
							}
						}
					],
					"request": {
						"method": "GET",
						"header": [],
						"body": {
							"mode": "raw",
							"raw": ""
						},
						"url": {
							"raw": "https://dreamteam-gateway.mybluemix.net/video-service/videos/2",
							"protocol": "https",
							"host": [
								"dreamteam-gateway",
								"mybluemix",
								"net"
							],
							"path": [
								"video-service",
								"videos",
								"2"
							]
						}
					},
					"response": []
				},
				{
					"name": "/video/{videoId}",
					"event": [
						{
							"listen": "test",
							"script": {
								"id": "371be581-7909-41e8-bf1b-47432ec5fcd1",
								"exec": [
									"pm.test(\"แสดง video ที่มี id 8263\", function(){",
									"    var jsonData = pm.response.json();",
									"    pm.expect(jsonData.videoId).to.eql(8263);",
									"})"
								],
								"type": "text/javascript"
							}
						}
					],
					"request": {
						"method": "GET",
						"header": [],
						"body": {
							"mode": "raw",
							"raw": ""
						},
						"url": {
							"raw": "https://dreamteam-gateway.mybluemix.net/video-service/video/8263",
							"protocol": "https",
							"host": [
								"dreamteam-gateway",
								"mybluemix",
								"net"
							],
							"path": [
								"video-service",
								"video",
								"8263"
							]
						}
					},
					"response": []
				}
			],
			"event": [
				{
					"listen": "prerequest",
					"script": {
						"id": "ceee0e80-bd09-4f15-974a-7c3f368352eb",
						"type": "text/javascript",
						"exec": [
							""
						]
					}
				},
				{
					"listen": "test",
					"script": {
						"id": "274a1e99-944a-479a-bfa9-2011383969d6",
						"type": "text/javascript",
						"exec": [
							""
						]
					}
				}
			]
		}
	]
}